rod/__init__.py
rod/__main__.py
rod/logging.py
rod/pretty_printer.py
rod/builder/__init__.py
rod/builder/primitive_builder.py
rod/builder/primitives.py
rod/kinematics/__init__.py
rod/kinematics/kinematic_tree.py
rod/kinematics/tree_transforms.py
rod/sdf/__init__.py
rod/sdf/collision.py
rod/sdf/common.py
rod/sdf/element.py
rod/sdf/geometry.py
rod/sdf/joint.py
rod/sdf/link.py
rod/sdf/material.py
rod/sdf/model.py
rod/sdf/physics.py
rod/sdf/scene.py
rod/sdf/sdf.py
rod/sdf/visual.py
rod/sdf/world.py
rod/tree/__init__.py
rod/tree/directed_tree.py
rod/tree/tree_elements.py
rod/urdf/__init__.py
rod/urdf/exporter.py
rod/utils/__init__.py
rod/utils/frame_convention.py
rod/utils/gazebo.py
rod/utils/resolve_frames.py
rod/utils/resolve_uris.py
rod-0.4.1.dist-info/licenses/LICENSE
rod-0.4.1.dist-info/METADATA
rod-0.4.1.dist-info/WHEEL
rod-0.4.1.dist-info/top_level.txt
rod-0.4.1.dist-info/RECORD
