Metadata-Version: 2.4
Name: rod
Version: 0.4.1
Summary: The ultimate Python tool for RObot Descriptions processing.
Author-email: Diego Ferigo <dgferigo@gmail.com>
Maintainer-email: Filippo Luca Ferretti <filippo.ferretti@iit.it>, Carlotta Sartore <carlotta.sartore@iit.it>
License: BSD 3-Clause License
Project-URL: Changelog, https://github.com/ami-iit/rod/releases
Project-URL: Source, https://github.com/ami-iit/rod
Project-URL: Tracker, https://github.com/ami-iit/rod/issues
Keywords: description,gazebo,parser,robot,robotics,ros,sdf,sdformat,simulator,simulation,urdf
Classifier: Development Status :: 5 - Production/Stable
Classifier: Framework :: Robot Framework
Classifier: Intended Audience :: Science/Research
Classifier: Intended Audience :: Developers
Classifier: Intended Audience :: Education
Classifier: License :: OSI Approved :: BSD License
Classifier: Operating System :: OS Independent
Classifier: Operating System :: POSIX :: Linux
Classifier: Operating System :: MacOS
Classifier: Operating System :: Microsoft :: Windows
Classifier: Programming Language :: Python :: 3
Classifier: Programming Language :: Python :: 3.10
Classifier: Programming Language :: Python :: 3.11
Classifier: Programming Language :: Python :: 3.12
Classifier: Programming Language :: Python :: 3.13
Classifier: Programming Language :: Python :: 3 :: Only
Classifier: Programming Language :: Python :: Implementation :: CPython
Classifier: Topic :: Games/Entertainment :: Simulation
Requires-Python: >=3.10
License-File: LICENSE
Requires-Dist: coloredlogs
Requires-Dist: mashumaro
Requires-Dist: numpy
Requires-Dist: packaging
Requires-Dist: resolve-robotics-uri-py
Requires-Dist: scipy
Requires-Dist: trimesh
Requires-Dist: xmltodict
Provides-Extra: style
Requires-Dist: black~=24.0; extra == "style"
Requires-Dist: isort; extra == "style"
Provides-Extra: pptree
Requires-Dist: pptree; extra == "pptree"
Provides-Extra: testing
Requires-Dist: idyntree>=12.2.1; extra == "testing"
Requires-Dist: pytest>=6.0; extra == "testing"
Requires-Dist: pytest-icdiff; extra == "testing"
Requires-Dist: robot-descriptions; extra == "testing"
Provides-Extra: all
Requires-Dist: rod[pptree,style,testing]; extra == "all"
Dynamic: license-file
